arkhive/__init__.py
arkhive-0.0.1.dist-info/LICENSE
arkhive-0.0.1.dist-info/METADATA
arkhive-0.0.1.dist-info/WHEEL
arkhive-0.0.1.dist-info/top_level.txt
arkhive-0.0.1.dist-info/RECORD
